WhiteStripe/__init__.py
WhiteStripe-0.0.1.dist-info/LICENSE
WhiteStripe-0.0.1.dist-info/METADATA
WhiteStripe-0.0.1.dist-info/WHEEL
WhiteStripe-0.0.1.dist-info/top_level.txt
WhiteStripe-0.0.1.dist-info/RECORD
