Metadata-Version: 2.1
Name: WhiteStripe
Version: 0.0.1
Summary: A wrapper for the WhiteStripe normalization R package
Home-page: https://github.com/PennSIVE/WhiteStripe.py
Author: Tim Robert-Fitzgerald
Author-email: timrf@upenn.edu
License: UNKNOWN
Platform: UNKNOWN
Classifier: Programming Language :: Python :: 3
Classifier: License :: OSI Approved :: MIT License
Classifier: Operating System :: OS Independent
Requires-Python: >=3.6
Requires-Dist: rpy2
